setup.py
cnf/__init__.py
cnf/cnfconverter.py
cnf/parsetab.py
cnfconverter.egg-info/PKG-INFO
cnfconverter.egg-info/SOURCES.txt
cnfconverter.egg-info/dependency_links.txt
cnfconverter.egg-info/requires.txt
cnfconverter.egg-info/top_level.txt