Metadata-Version: 1.0
Name: cnfconverter
Version: 1.1.1
Summary: CNF sdk
Home-page: http://panjinbo.com
Author: Jinbo Pan
Author-email: pan.jinbo@outlook.com
License: UNKNOWN
Keywords: pip,datacanvas,cnf,panjinbo
Platform: any
